{
  "pack": "ES_PACK02_Basics",
  "grade": 3,
  "semester": 1,
  "unit": 1,
  "pdf_key": "3-1",
  "title": "1단원. 덧셈과 뺄셈",
  "total_problems": 30,
  "categories": [
    {
      "id": "1",
      "name": "1단원. 덧셈과 뺄셈",
      "range": [1, 30],
      "problems": [
        {"id": 1, "question": "문구점에서 연필 245자루, 지우개 178개를 들여왔습니다. 둘을 합치면 물건이 모두 몇 개인가요?", "concept": "덧셈과 뺄셈 · 기본 계산", "difficulty": "중", "answer": "423개"},
        {"id": 2, "question": "운동회 준비로 물 326병이 있었는데 189병을 나누어 주었습니다. 남은 물은 몇 병인가요?", "concept": "덧셈과 뺄셈 · 기본 계산", "difficulty": "중", "answer": "137병"},
        {"id": 3, "question": "도서관에 새 책 408권이 들어왔고, 그중 275권은 어린이 코너로 옮겼습니다. 다른 코너로 남는 책은 몇 권인가요?", "concept": "덧셈과 뺄셈 · 기본 계산", "difficulty": "중", "answer": "133권"},
        {"id": 4, "question": "A반은 종이학을 154개, B반은 169개 접었습니다. 두 반이 접은 종이학은 모두 몇 개인가요?", "concept": "덧셈과 뺄셈 · 기본 계산", "difficulty": "하", "answer": "323개"},
        {"id": 5, "question": "마을 축제 쿠폰이 600장 있었는데 오전에 238장, 오후에 197장을 나눠 주었습니다. 남은 쿠폰은 몇 장인가요?", "concept": "덧셈과 뺄셈 · 기본 계산", "difficulty": "중", "answer": "165장"},
        {"id": 6, "question": "급식실에 사과 352개가 있었는데, 1학년에게 128개, 2학년에게 97개를 주었습니다. 남은 사과는 몇 개인가요?", "concept": "덧셈과 뺄셈 · 기본 계산", "difficulty": "중", "answer": "127개"},
        {"id": 7, "question": "버스에 처음 187명이 타고 있었고, 정류장에서 96명이 더 탔습니다. 그다음 정류장에서 143명이 내렸습니다. 지금 버스에 남은 사람은 몇 명인가요?", "concept": "덧셈과 뺄셈 · 기본 계산", "difficulty": "중", "answer": "140명"},
        {"id": 8, "question": "학급 모금함에 첫째 날 2750원, 둘째 날 1890원을 넣었습니다. 이틀 모금액은 모두 얼마인가요?", "concept": "덧셈과 뺄셈 · 기본 계산", "difficulty": "중", "answer": "4640원"},
        {"id": 9, "question": "소풍 간식으로 과자 430개를 준비했는데 비가 와서 165개를 창고로 다시 옮겼습니다. 남아 나눠 줄 수 있는 과자는 몇 개인가요?", "concept": "덧셈과 뺄셈 · 기본 계산", "difficulty": "하", "answer": "265개"},
        {"id": 10, "question": "책상 정리함에 스티커가 218장 있었고, 친구가 75장을 더 주었습니다. 그중 143장을 나누어 주면 몇 장이 남나요?", "concept": "덧셈과 뺄셈 · 기본 계산", "difficulty": "중", "answer": "150장"},
        {"id": 11, "question": "수학 문제집 395쪽 중 오늘 128쪽을 풀었습니다. 남은 쪽수는 몇 쪽인가요?", "concept": "덧셈과 뺄셈 · 기본 계산", "difficulty": "하", "answer": "267쪽"},
        {"id": 12, "question": "체육관에 의자가 480개 있었는데 215개를 다른 행사장으로 옮겼습니다. 남은 의자는 몇 개인가요?", "concept": "덧셈과 뺄셈 · 기본 계산", "difficulty": "하", "answer": "265개"},
        {"id": 13, "question": "과일 바구니에 귤 167개와 포도 209송이가 있습니다. 합쳐서 \"과일(단위가 다르면 안 됨)\"이라고 말할 수 있을까요? 가능/불가능을 이유와 함께 쓰세요.", "concept": "덧셈과 뺄셈 · 단위 이해", "difficulty": "상", "answer": "불가능합니다. 귤은 '개', 포도는 '송이'로 단위가 다르기 때문에 그대로 더할 수 없습니다"},
        {"id": 14, "question": "저금통에 500원짜리 3개와 100원짜리 7개를 넣었습니다. 모두 얼마인가요?", "concept": "덧셈과 뺄셈 · 기본 계산", "difficulty": "하", "answer": "2200원"},
        {"id": 15, "question": "학급 게시판에 안내문 286장을 붙였는데 39장이 떨어졌습니다. 다시 붙이려면 최소 몇 장이 필요할까요?", "concept": "덧셈과 뺄셈 · 기본 계산", "difficulty": "하", "answer": "39장"},
        {"id": 16, "question": "A상자에 234개, B상자에 234개, C상자에 98개가 있습니다. 세 상자에 들어 있는 물건은 모두 몇 개인가요?", "concept": "덧셈과 뺄셈 · 기본 계산", "difficulty": "하", "answer": "566개"},
        {"id": 17, "question": "양말이 420켤레 있었는데 주문이 199켤레 들어왔습니다. 주문을 처리하고 남는 양말은 몇 켤레인가요?", "concept": "덧셈과 뺄셈 · 기본 계산", "difficulty": "중", "answer": "221켤레"},
        {"id": 18, "question": "체험학습 신청자가 312명인데 그중 158명이 점심을 신청했습니다. 점심을 신청하지 않은 학생은 몇 명인가요?", "concept": "덧셈과 뺄셈 · 기본 계산", "difficulty": "하", "answer": "154명"},
        {"id": 19, "question": "우유 365팩을 냉장고에 넣었고, 추가로 87팩을 더 넣었습니다. 그날 214팩을 마셨다면 남은 우유는 몇 팩인가요?", "concept": "덧셈과 뺄셈 · 기본 계산", "difficulty": "중", "answer": "238팩"},
        {"id": 20, "question": "길거리 행사에서 풍선 500개 중 275개를 나눠 주었습니다. 남은 풍선 수를 \"대략\"으로 어림해 말하고, 어림한 이유를 한 줄로 쓰세요.", "concept": "덧셈과 뺄셈 · 어림하기", "difficulty": "중", "answer": "약 200개 (또는 약 225개). 정확한 계산 없이 빠르게 대략적인 수를 알기 위해 어림합니다"},
        {"id": 21, "question": "학급 SNS에 사진이 148장 올라왔고, 선생님이 67장을 더 올렸습니다. 그중 95장을 삭제하면 몇 장이 남나요?", "concept": "덧셈과 뺄셈 · 기본 계산", "difficulty": "하", "answer": "120장"},
        {"id": 22, "question": "놀이터 청소로 쓰레기봉투 173개를 모았고, 다음 날 168개를 더 모았습니다. 합계는 몇 개인가요?", "concept": "덧셈과 뺄셈 · 기본 계산", "difficulty": "하", "answer": "341개"},
        {"id": 23, "question": "3학년 전체가 우유팩을 389개 모았는데 분리수거장에 250개를 먼저 가져갔습니다. 남은 것은 몇 개인가요?", "concept": "덧셈과 뺄셈 · 기본 계산", "difficulty": "하", "answer": "139개"},
        {"id": 24, "question": "마라톤 참가번호가 1번부터 485번까지라면 참가자는 몇 명인가요? (번호가 연속이라고 가정)", "concept": "덧셈과 뺄셈 · 기본 계산", "difficulty": "중", "answer": "485명"},
        {"id": 25, "question": "수영장 입장객이 오전 196명, 오후 207명입니다. 오늘 입장객은 모두 몇 명인가요?", "concept": "덧셈과 뺄셈 · 기본 계산", "difficulty": "하", "answer": "403명"},
        {"id": 26, "question": "편의점에서 물 125병을 팔고, 다음 날 98병을 더 팔았습니다. 이틀 동안 팔린 물은 모두 몇 병인가요?", "concept": "덧셈과 뺄셈 · 기본 계산", "difficulty": "하", "answer": "223병"},
        {"id": 27, "question": "택배 상자가 600개 도착했는데 375개를 먼저 분류했습니다. 아직 분류하지 않은 상자는 몇 개인가요?", "concept": "덧셈과 뺄셈 · 기본 계산", "difficulty": "하", "answer": "225개"},
        {"id": 28, "question": "친구 3명이 모은 도토리가 각각 145개, 168개, 129개입니다. 세 사람이 모은 도토리는 모두 몇 개인가요?", "concept": "덧셈과 뺄셈 · 기본 계산", "difficulty": "중", "answer": "442개"},
        {"id": 29, "question": "기부 상자에 장난감 410개가 있었는데 새로 95개가 들어왔습니다. 그중 230개를 보내면 남은 장난감은 몇 개인가요?", "concept": "덧셈과 뺄셈 · 기본 계산", "difficulty": "중", "answer": "275개"},
        {"id": 30, "question": "어떤 수에 189를 더하면 430이 됩니다. 그 수는 얼마인가요? (이유를 말로 쓰세요)", "concept": "덧셈과 뺄셈 · 기본 계산", "difficulty": "중", "answer": "241입니다. 430에서 189를 빼면 됩니다"}
      ]
    }
  ],
  "note": "초등 3학년 1학기 1단원 덧셈과 뺄셈 - 30문항",
  "created_date": "2026-01-15",
  "source": "UserProvided_3-1_Unit1_AdditionSubtraction",
  "version": "1.0",
  "structure": "1단원 덧셈과 뺄셈 - 30문항"
}

